{"assets":{"458AE5A41E6276C8513863164599BBC3":{"type":"texture","index":1,"assetRequest":{"type":"slide","state":"contents","slide":"none"},"url":{"native":"assets\/9479CC1E-C0FD-4302-949F-D7089DDCFC90.pdf"},"width":1920,"height":1080},"061363E26CFD10E774A6FC74719486CB":{"type":"texture","index":0,"assetRequest":{"type":"slide","state":"contents","slide":"none"},"url":{"native":"assets\/9479CC1E-C0FD-4302-949F-D7089DDCFC90.pdf"},"width":1920,"height":1080}},"events":[{"effects":[{"beginTime":0,"baseLayer":{"animations":[],"initialState":{"affineTransform":[1,0,0,1,0,0],"masksToBounds":false,"rotation":0,"scale":1,"position":{"pointX":960,"pointY":540},"width":1920,"sublayerTransform":[1,0,0,0,0,1,0,0,0,0,1,0,0,0,0,1],"contentsRect":{"y":0,"x":0,"width":1,"height":1},"opacity":1,"edgeAntialiasingMask":251658240,"height":1080,"hidden":false,"anchorPoint":{"pointX":0.5,"pointY":0.5}},"objectID":"0","layers":[{"animations":[],"initialState":{"affineTransform":[1,0,0,1,0,0],"masksToBounds":false,"rotation":0,"scale":1,"position":{"pointX":960,"pointY":540},"width":1920,"sublayerTransform":[1,0,0,0,0,1,0,0,0,0,1,-0.00035007912466775983,0,0,0,1],"contentsRect":{"y":0,"x":0,"width":1,"height":1},"opacity":1,"edgeAntialiasingMask":251658240,"height":1080,"hidden":false,"anchorPoint":{"pointX":0.5,"pointY":0.5}},"layers":[{"animations":[],"layers":[],"texturedRectangle":{"isBackgroundTexture":false,"singleTextureOpacity":1,"textureType":0,"textBaseline":0,"textXHeight":0,"isVerticalText":false},"initialState":{"affineTransform":[1,0,0,1,0,0],"masksToBounds":false,"rotation":0,"scale":1,"position":{"pointX":960,"pointY":540},"width":1920,"sublayerTransform":[1,0,0,0,0,1,0,0,0,0,1,0,0,0,0,1],"contentsRect":{"y":0,"x":0,"width":1,"height":1},"opacity":1,"edgeAntialiasingMask":0,"height":1080,"hidden":false,"anchorPoint":{"pointX":0.5,"pointY":0.5}},"texture":"458AE5A41E6276C8513863164599BBC3"},{"animations":[{"timeOffset":0,"from":{"scalar":false},"beginTime":0,"repeatCount":0,"fillMode":"both","property":"hidden","autoreverses":false,"duration":0.01,"to":{"scalar":true}}],"layers":[],"texturedRectangle":{"isBackgroundTexture":false,"singleTextureOpacity":1,"textureType":0,"textBaseline":0,"textXHeight":0,"isVerticalText":false},"initialState":{"affineTransform":[1,0,0,1,0,0],"masksToBounds":false,"rotation":0,"scale":1,"position":{"pointX":960,"pointY":540},"width":1920,"sublayerTransform":[1,0,0,0,0,1,0,0,0,0,1,0,0,0,0,1],"contentsRect":{"y":0,"x":0,"width":1,"height":1},"opacity":1,"edgeAntialiasingMask":0,"height":1080,"hidden":false,"anchorPoint":{"pointX":0.5,"pointY":0.5}},"texture":"061363E26CFD10E774A6FC74719486CB"}]}]},"effects":[],"duration":0.01,"type":"transition","attributes":{"direction":0},"name":"none","objectID":"0"}],"automaticPlay":false,"hyperlinks":[{"url":"https:\/\/www.investopedia.com\/articles\/trading\/07\/stationary.asp","targetRectangle":{"y":332.33984375,"x":896.44981103515624,"width":458.36800000000017,"height":17.552001953125}},{"url":"https:\/\/fat-pitch.blogspot.com\/2019\/04\/summary-ndx-is-now-at-new-all-time-high.html","targetRectangle":{"y":1029.97314453125,"x":873.62283239746102,"width":624.75200000000018,"height":17.552001953125}},{"url":"http:\/\/stockcharts.com","targetRectangle":{"y":1029.97314453125,"x":1547.8788323974611,"width":119.4399999999996,"height":17.552001953125}}],"accessibility":[{"text":"source (left): https:\/\/www.investopedia.com\/articles\/trading\/07\/stationary.asp ","targetRectangle":{"y":332.33984375,"x":804.59381103515625,"width":554.67200000000003,"height":17.552001953125}},{"text":"S&P500 index","targetRectangle":{"y":638.0101318359375,"x":1382.0189208984375,"width":100.76800000000003,"height":17.552001953125}},{"text":"S&P500 volatility index (VIX)","targetRectangle":{"y":674.0101318359375,"x":1382.0189208984375,"width":199.71199999999999,"height":17.552001953125}},{"text":"Low vix.png","targetRectangle":{"y":361.8505859375,"x":565.938232421875,"width":1108.4017333984375,"height":623.677978515625}},{"text":"source (lower): The Fat Pitch blog, https:\/\/fat-pitch.blogspot.com\/2019\/04\/summary-ndx-is-now-at-new-all-time-high.html, data: stockcharts.com ","targetRectangle":{"y":1029.97314453125,"x":625.31883239746094,"width":1046.4480000000001,"height":17.552001953125}},{"text":"background-red.png","targetRectangle":{"y":-0.60978984832763672,"x":240,"width":1440,"height":540}},{"text":"4. Behavioral example: Skewness of returns","targetRectangle":{"y":10.896156549453735,"x":395.07200000000012,"width":1129.8559999999998,"height":67.3756103515625}},{"text":"background-red.png","targetRectangle":{"y":-0.60978984832763672,"x":1663.99609375,"width":1440,"height":540}},{"text":"Skew is time dependent, as financial data is not stationary","targetRectangle":{"y":182.26945348815934,"x":297.79623413085938,"width":745.61199999999985,"height":40.80572668685636}},{"text":"AT-Stationary1-5bfd88bd46e0fb0051fd0786.gif","targetRectangle":{"y":219.53678894042969,"x":254.80296325683594,"width":547.03125,"height":379.6875}},{"text":"background-red.png","targetRectangle":{"y":-0.60978949069976807,"x":-1187.356201171875,"width":1440,"height":540}}],"baseLayer":{"animations":[],"initialState":{"affineTransform":[1,0,0,1,0,0],"masksToBounds":false,"rotation":0,"scale":1,"position":{"pointX":960,"pointY":540},"width":1920,"sublayerTransform":[1,0,0,0,0,1,0,0,0,0,1,0,0,0,0,1],"contentsRect":{"y":0,"x":0,"width":1,"height":1},"opacity":1,"edgeAntialiasingMask":251658240,"height":1080,"hidden":false,"anchorPoint":{"pointX":0.5,"pointY":0.5}},"objectID":"0","layers":[{"animations":[],"initialState":{"affineTransform":[1,0,0,1,0,0],"masksToBounds":false,"rotation":0,"scale":1,"position":{"pointX":960,"pointY":540},"width":1920,"sublayerTransform":[1,0,0,0,0,1,0,0,0,0,1,-0.00035007912466775983,0,0,0,1],"contentsRect":{"y":0,"x":0,"width":1,"height":1},"opacity":1,"edgeAntialiasingMask":251658240,"height":1080,"hidden":false,"anchorPoint":{"pointX":0.5,"pointY":0.5}},"layers":[{"animations":[],"layers":[],"texturedRectangle":{"isBackgroundTexture":false,"singleTextureOpacity":1,"textureType":0,"textBaseline":0,"textXHeight":0,"isVerticalText":false},"initialState":{"affineTransform":[1,0,0,1,0,0],"masksToBounds":false,"rotation":0,"scale":1,"position":{"pointX":960,"pointY":540},"width":1920,"sublayerTransform":[1,0,0,0,0,1,0,0,0,0,1,0,0,0,0,1],"contentsRect":{"y":0,"x":0,"width":1,"height":1},"opacity":1,"edgeAntialiasingMask":0,"height":1080,"hidden":false,"anchorPoint":{"pointX":0.5,"pointY":0.5}},"texture":"061363E26CFD10E774A6FC74719486CB"}]}]}}]}